MANIFEST.in
README.rst
setup.py
PyCygwin.egg-info/PKG-INFO
PyCygwin.egg-info/SOURCES.txt
PyCygwin.egg-info/dependency_links.txt
PyCygwin.egg-info/top_level.txt
cygwin/__init__.py
cygwin/_cygwin.pxd
cygwin/_cygwin.pyx