Metadata-Version: 1.0
Name: PyCygwin
Version: 0.1
Summary: Python bindings for Cygwin's C API
Home-page: https://github.com/embray/PyCygwin
Author: E. M. Bray
Author-email: erik.m.bray@gmail.com
License: BSD
Platform: UNKNOWN
